yubistack/__init__.py
yubistack/config.py
yubistack/crypt.py
yubistack/db.py
yubistack/exceptions.py
yubistack/replicate.py
yubistack/softtoken.py
yubistack/utils.py
yubistack/wsgi.py
yubistack/ykauth.py
yubistack/ykksm.py
yubistack/yksync.py
yubistack/ykval.py
yubistack-1.0.0.dist-info/LICENSE
yubistack-1.0.0.dist-info/METADATA
yubistack-1.0.0.dist-info/WHEEL
yubistack-1.0.0.dist-info/top_level.txt
yubistack-1.0.0.dist-info/RECORD
